{
    "experiment": {
        "name": "CIFAR 10",
        "tags": ["vgg16", "cifar-10"]
    },
    "model": {
        "description": "Transfer Learning using VGG16 for CIFAR-10 dataset",
        "input_shape": [32, 32, 3],
        "network": [
            {"type": "application", "application": "vgg16", "include_top": true, "classes": 10, "weights": null}
        ],
        "compilation": {
            "optimizer": {
                "type": "sgd",
                "lr": 0.01
            },
            "loss": "categorical_crossentropy",
            "metrics": ["acc"]
        }
    },
    "dataset": {
        "id": "cifar10"
    },
    "training": {
        "samples": {
            "fit": 0.6,
            "val": 0.2,
            "test": 0.2
        },
        "batch_size": 32,
        "epochs": 10,
        "callbacks": [
            {
                "type": "early_stopping"
            }
        ]
    },
    "tracking": {
        "trackers": [
            {
                "type": "tensorboard",
                "logdir": "tensorboard"
            },
            {
                "type": "mlflow",
                "run_name": "cifar10"
            }
        ]
    }
}
